AUTHORS.rst
CONTRIBUTING.rst
HISTORY.rst
LICENSE
MANIFEST.in
README.rst
setup.cfg
setup.py
django_outlook/__init__.py
django_outlook/admin.py
django_outlook/default_settings.py
django_outlook/models.py
django_outlook/urls.py
django_outlook/views.py
django_outlook.egg-info/PKG-INFO
django_outlook.egg-info/SOURCES.txt
django_outlook.egg-info/dependency_links.txt
django_outlook.egg-info/not-zip-safe
django_outlook.egg-info/top_level.txt
django_outlook/management/__init__.py
django_outlook/management/mail_to_handle_base.py
django_outlook/management/o365mail.py
django_outlook/management/outlook_mail.py
django_outlook/migrations/0001_initial.py
django_outlook/migrations/0002_auto_20180628_1240.py
django_outlook/migrations/__init__.py
django_outlook/o365_utils/__init__.py
django_outlook/o365_utils/adv_connection.py
django_outlook/o365_utils/fluent_inbox_adv.py
django_outlook/o365_utils/fluent_message_adv.py
django_outlook/o365_utils/login_token_storage.py
django_outlook/o365_utils/mailbox_adv.py
django_outlook/o365_utils/o365_url_generator.py
django_outlook/o365_utils/token_storage.py
django_outlook/templates/django_outlook/key_got.html
django_outlook/templates/django_outlook/login_form.html
docs/Makefile
docs/authors.rst
docs/conf.py
docs/contributing.rst
docs/history.rst
docs/index.rst
docs/installation.rst
docs/make.bat
docs/readme.rst
docs/usage.rst
tests/__init__.py
tests/test_django_outlook.py