Metadata-Version: 1.1
Name: django-outlook
Version: 0.1.1
Summary: Operate outlook mail from Django
Home-page: https://github.com/weijia/django-outlook
Author: Richard Wang
Author-email: richardwangwang@gmail.com
License: MIT license
Keywords: django_outlook
Platform: UNKNOWN
Classifier: Development Status :: 2 - Pre-Alpha
Classifier: Intended Audience :: Developers
Classifier: License :: OSI Approved :: MIT License
Classifier: Natural Language :: English
Classifier: Programming Language :: Python :: 2
Classifier: Programming Language :: Python :: 2.7
Classifier: Programming Language :: Python :: 3
Classifier: Programming Language :: Python :: 3.4
Classifier: Programming Language :: Python :: 3.5
Classifier: Programming Language :: Python :: 3.6
Classifier: Programming Language :: Python :: 3.7
